<annotation>
	<folder>my-project-name</folder>
	<filename>00094.jpg</filename>
	<path>/my-project-name/00094.jpg</path>
	<source>
		<database>Unspecified</database>
	</source>
	<size>
		<width>600</width>
		<height>311</height>
		<depth>3</depth>
	</size>
	<object>
		<name>Ethernet</name>
		<pose>Unspecified</pose>
		<truncated>Unspecified</truncated>
		<difficult>Unspecified</difficult>
		<bndbox>
			<xmin>405</xmin>
			<ymin>125</ymin>
			<xmax>447</xmax>
			<ymax>158</ymax>
		</bndbox>
	</object>
	<object>
		<name>VGA</name>
		<pose>Unspecified</pose>
		<truncated>Unspecified</truncated>
		<difficult>Unspecified</difficult>
		<bndbox>
			<xmin>275</xmin>
			<ymin>173</ymin>
			<xmax>320</xmax>
			<ymax>194</ymax>
		</bndbox>
	</object>
	<object>
		<name>DVI</name>
		<pose>Unspecified</pose>
		<truncated>Unspecified</truncated>
		<difficult>Unspecified</difficult>
		<bndbox>
			<xmin>169</xmin>
			<ymin>176</ymin>
			<xmax>230</xmax>
			<ymax>197</ymax>
		</bndbox>
	</object>
</annotation>